saara/__init__.py
saara/accelerator.py
saara/ai_tokenizer.py
saara/api.py
saara/chunker.py
saara/cleaner.py
saara/cli.py
saara/cloud_runtime.py
saara/dataset_generator.py
saara/deployer.py
saara/distiller.py
saara/evaluator.py
saara/gpu_workers.py
saara/labeler.py
saara/model_manager.py
saara/moondream_ocr.py
saara/ollama_client.py
saara/pdf_extractor.py
saara/pipeline.py
saara/pretrain.py
saara/pretrain_data.py
saara/qwen_ocr.py
saara/rag_engine.py
saara/splash.py
saara/synthetic_generator.py
saara/train.py
saara/translator.py
saara/visualizer.py
saara/workspace.py
saara_ai-1.6.3.dist-info/licenses/LICENSE
saara_ai-1.6.3.dist-info/METADATA
saara_ai-1.6.3.dist-info/WHEEL
saara_ai-1.6.3.dist-info/entry_points.txt
saara_ai-1.6.3.dist-info/top_level.txt
saara_ai-1.6.3.dist-info/RECORD
