Metadata-Version: 2.4
Name: saara-ai
Version: 1.6.3
Summary: 🧠 SAARA - Autonomous Document-to-LLM Data Engine with Pre-training, Cloud Runtime & AI Tokenizer
Home-page: https://github.com/nikhil49023/Data-engine
Author: Kilani Sai Nikhil
Author-email: Kilani Sai Nikhil <nikhil49023@gmail.com>
Maintainer-email: Kilani Sai Nikhil <nikhil49023@gmail.com>
License: SAARA-AI Proprietary License
Project-URL: Homepage, https://github.com/nikhil49023/Data-engine
Project-URL: Repository, https://github.com/nikhil49023/Data-engine
Keywords: llm,fine-tuning,gemini,gemma,google-ai,pdf,dataset,ai,machine-learning,nlp,training-data,synthetic-data,document-processing,ocr,vision-language,transformers,lora,qlora,tokenizer,cloud-runtime,colab
Classifier: Development Status :: 4 - Beta
Classifier: Environment :: Console
Classifier: Intended Audience :: Developers
Classifier: Intended Audience :: Science/Research
Classifier: License :: Other/Proprietary License
Classifier: Operating System :: OS Independent
Classifier: Programming Language :: Python :: 3
Classifier: Programming Language :: Python :: 3.10
Classifier: Programming Language :: Python :: 3.11
Classifier: Programming Language :: Python :: 3.12
Classifier: Programming Language :: Python :: 3.13
Classifier: Topic :: Scientific/Engineering :: Artificial Intelligence
Classifier: Topic :: Text Processing :: General
Classifier: Typing :: Typed
Requires-Python: >=3.8
License-File: LICENSE
Requires-Dist: typer[all]>=0.9.0
Requires-Dist: rich>=13.0.0
Requires-Dist: PyYAML>=6.0
Requires-Dist: requests>=2.28.0
Requires-Dist: PyMuPDF>=1.23.0
Requires-Dist: Pillow>=10.0.0
Requires-Dist: tqdm>=4.65.0
Requires-Dist: fastapi>=0.100.0
Requires-Dist: uvicorn>=0.22.0
Requires-Dist: pydantic>=2.0.0
Requires-Dist: python-multipart>=0.0.6
Requires-Dist: psutil>=5.9.0
Requires-Dist: httpx>=0.24.0
Requires-Dist: pdfplumber>=0.10.0
Requires-Dist: ollama>=0.3.0
Requires-Dist: pandas>=2.0.0
Requires-Dist: torch>=2.0.0
Requires-Dist: transformers>=4.35.0
Requires-Dist: datasets>=2.14.0
Requires-Dist: peft>=0.6.0
Requires-Dist: trl>=0.7.0
Requires-Dist: bitsandbytes>=0.41.0
Requires-Dist: accelerate>=0.24.0
Requires-Dist: google-generativeai>=0.8.0
Requires-Dist: sentencepiece>=0.1.99
Provides-Extra: dev
Requires-Dist: pytest>=7.0.0; extra == "dev"
Requires-Dist: black>=23.0.0; extra == "dev"
Requires-Dist: isort>=5.12.0; extra == "dev"
Provides-Extra: all
Requires-Dist: saara[dev,train]; extra == "all"
Dynamic: author
Dynamic: home-page
Dynamic: license-file
Dynamic: requires-python
